{
  "current_elo": 1500.0,
  "divisional_rank": 423,
  "fight_count": 2,
  "fight_log": [
    {
      "blue_name": "Carlos Eduardo",
      "bout_type": "Light Heavyweight Bout",
      "date": "2021-07-16",
      "elo_delta": -18.4,
      "event_name": "Legacy Fighting Alliance 111: De Sa vs. Bonfim",
      "fight_id": "33694b73941bec06",
      "gender": "men",
      "is_title": false,
      "method": "Submission (rear-naked choke)",
      "opponent": "Rodolfo Bellato",
      "opponent_elo": 1500.0,
      "outcome": "red_win",
      "post_elo": 1462.2,
      "pre_elo": 1480.6,
      "red_name": "Rodolfo Bellato",
      "round": "1",
      "time": "3:05",
      "weight_class": "Light Heavyweight"
    },
    {
      "blue_name": "Carlos Eduardo",
      "bout_type": "Light Heavyweight 93 kg Bout",
      "date": "2005-09-10",
      "elo_delta": -19.4,
      "event_name": "KSW IV: Konfrontacja",
      "fight_id": "8c0f13f7021b06d7",
      "gender": "men",
      "is_title": false,
      "method": "KO (Punch)",
      "opponent": "Damir Mirenic",
      "opponent_elo": 1500.0,
      "outcome": "red_win",
      "post_elo": 1480.6,
      "pre_elo": 1500.0,
      "red_name": "Damir Mirenic",
      "round": "2",
      "time": "Tournament Quarter-Finals 4",
      "weight_class": "Light Heavyweight"
    }
  ],
  "first_fight_date": "2005-09-10",
  "gender": "men",
  "history": [
    {
      "date": "2005-09-10",
      "fight_id": "8c0f13f7021b06d7",
      "rating": 1480.6,
      "scope": "division",
      "system": "men:Light Heavyweight"
    },
    {
      "date": "2005-09-10",
      "fight_id": "8c0f13f7021b06d7",
      "rating": 1482.7,
      "scope": "overall",
      "system": "men:overall"
    },
    {
      "date": "2021-07-16",
      "fight_id": "33694b73941bec06",
      "rating": 1462.2,
      "scope": "division",
      "system": "men:Light Heavyweight"
    },
    {
      "date": "2021-07-16",
      "fight_id": "33694b73941bec06",
      "rating": 1466.3,
      "scope": "overall",
      "system": "men:overall"
    }
  ],
  "instagram": null,
  "instagram_featured": false,
  "last_fight_date": "2021-07-16",
  "name": "Carlos Eduardo",
  "nickname": "",
  "overall_elo": 1500.0,
  "peak_elo": 1500.0,
  "slug": "carlos-eduardo",
  "systems": {
    "division": "men:Light Heavyweight",
    "overall": "men:overall"
  },
  "weight_class": "Light Heavyweight"
}
