{
  "current_elo": 1500.0,
  "divisional_rank": 446,
  "fight_count": 5,
  "fight_log": [
    {
      "blue_name": "Ilyas Musaev",
      "bout_type": "Bantamweight Muay Thai Bout",
      "date": "2023-12-08",
      "elo_delta": -18.2,
      "event_name": "ONE Friday Fights 44: Yod-IQ vs. Musaev",
      "fight_id": "bb4803e00a591158",
      "gender": "men",
      "is_title": false,
      "method": "Decision (split)",
      "opponent": "Yod-IQ Or.Pimonsri",
      "opponent_elo": 1500.0,
      "outcome": "red_win",
      "post_elo": 1485.4,
      "pre_elo": 1503.6,
      "red_name": "Yod-IQ Or.Pimonsri",
      "round": "3",
      "time": "3:00",
      "weight_class": "Bantamweight"
    },
    {
      "blue_name": "Otop Or.Kwanmuang",
      "bout_type": "Bantamweight Muay Thai Bout",
      "date": "2023-10-27",
      "elo_delta": 21.4,
      "event_name": "ONE Friday Fights 38: Otop vs. Musaev",
      "fight_id": "09ffa2f7e10f2557",
      "gender": "men",
      "is_title": false,
      "method": "KO (right hook)",
      "opponent": "Otop Or.Kwanmuang",
      "opponent_elo": 1517.3,
      "outcome": "red_win",
      "post_elo": 1503.6,
      "pre_elo": 1482.2,
      "red_name": "Ilyas Musaev",
      "round": "1",
      "time": "2:59",
      "weight_class": "Bantamweight"
    },
    {
      "blue_name": "Ilyas Musaev",
      "bout_type": "Bantamweight Muay Thai Bout",
      "date": "2023-08-04",
      "elo_delta": -18.2,
      "event_name": "ONE Friday Fights 27: Tapaokaew vs. Harrison",
      "fight_id": "f0d24a84f4907f32",
      "gender": "men",
      "is_title": false,
      "method": "Decision (unanimous)",
      "opponent": "Ferrari Fairtex",
      "opponent_elo": 1495.7,
      "outcome": "red_win",
      "post_elo": 1482.2,
      "pre_elo": 1500.4,
      "red_name": "Ferrari Fairtex",
      "round": "3",
      "time": "3:00",
      "weight_class": "Bantamweight"
    },
    {
      "blue_name": "Ilyas Musaev",
      "bout_type": "Bantamweight Muay Thai Bout",
      "date": "2023-03-03",
      "elo_delta": -19.0,
      "event_name": "ONE Friday Fights 7: Rambolek vs. Theeradet",
      "fight_id": "4357945c5627dc0f",
      "gender": "men",
      "is_title": false,
      "method": "Decision (unanimous)",
      "opponent": "Yodphupha Tor.Yotha",
      "opponent_elo": 1500.0,
      "outcome": "red_win",
      "post_elo": 1500.4,
      "pre_elo": 1519.4,
      "red_name": "Yodphupha Tor.Yotha",
      "round": "3",
      "time": "3:00",
      "weight_class": "Bantamweight"
    },
    {
      "blue_name": "Phanrith Lookjaomaesaiwaree",
      "bout_type": "Bantamweight Muay Thai Bout",
      "date": "2023-02-03",
      "elo_delta": 19.4,
      "event_name": "ONE Friday Fights 3: Chorfah vs. Phetsukumvit",
      "fight_id": "be2b8c12034dd9f2",
      "gender": "men",
      "is_title": false,
      "method": "KO (punch)",
      "opponent": "Phanrith Lookjaomaesaiwaree",
      "opponent_elo": 1500.0,
      "outcome": "red_win",
      "post_elo": 1519.4,
      "pre_elo": 1500.0,
      "red_name": "Ilyas Musaev",
      "round": "2",
      "time": "1:03",
      "weight_class": "Bantamweight"
    }
  ],
  "first_fight_date": "2023-02-03",
  "gender": "men",
  "history": [
    {
      "date": "2023-02-03",
      "fight_id": "be2b8c12034dd9f2",
      "rating": 1519.4,
      "scope": "division",
      "system": "men:Bantamweight"
    },
    {
      "date": "2023-02-03",
      "fight_id": "be2b8c12034dd9f2",
      "rating": 1517.3,
      "scope": "overall",
      "system": "men:overall"
    },
    {
      "date": "2023-03-03",
      "fight_id": "4357945c5627dc0f",
      "rating": 1500.4,
      "scope": "division",
      "system": "men:Bantamweight"
    },
    {
      "date": "2023-03-03",
      "fight_id": "4357945c5627dc0f",
      "rating": 1500.5,
      "scope": "overall",
      "system": "men:overall"
    },
    {
      "date": "2023-08-04",
      "fight_id": "f0d24a84f4907f32",
      "rating": 1482.2,
      "scope": "division",
      "system": "men:Bantamweight"
    },
    {
      "date": "2023-08-04",
      "fight_id": "f0d24a84f4907f32",
      "rating": 1483.3,
      "scope": "overall",
      "system": "men:overall"
    },
    {
      "date": "2023-10-27",
      "fight_id": "09ffa2f7e10f2557",
      "rating": 1503.6,
      "scope": "division",
      "system": "men:Bantamweight"
    },
    {
      "date": "2023-10-27",
      "fight_id": "09ffa2f7e10f2557",
      "rating": 1502.3,
      "scope": "overall",
      "system": "men:overall"
    },
    {
      "date": "2023-12-08",
      "fight_id": "bb4803e00a591158",
      "rating": 1485.4,
      "scope": "division",
      "system": "men:Bantamweight"
    },
    {
      "date": "2023-12-08",
      "fight_id": "bb4803e00a591158",
      "rating": 1486.2,
      "scope": "overall",
      "system": "men:overall"
    }
  ],
  "instagram": null,
  "instagram_featured": false,
  "last_fight_date": "2023-12-08",
  "name": "Ilyas Musaev",
  "nickname": "",
  "overall_elo": 1500.0,
  "peak_elo": 1519.4,
  "slug": "ilyas-musaev",
  "systems": {
    "division": "men:Bantamweight",
    "overall": "men:overall"
  },
  "weight_class": "Bantamweight"
}
