{
  "current_elo": 1500.0,
  "divisional_rank": 715,
  "fight_count": 1,
  "fight_log": [
    {
      "blue_name": "Jarrod Kwitty",
      "bout_type": "Middleweight Bout",
      "date": "2006-10-12",
      "elo_delta": -20.4,
      "event_name": "WEC 24: Full Force",
      "fight_id": "756a4a1d70fe97cb",
      "gender": "men",
      "is_title": false,
      "method": "TKO (Punches)",
      "opponent": "Patrick Kaase",
      "opponent_elo": 1482.0,
      "outcome": "red_win",
      "post_elo": 1479.6,
      "pre_elo": 1500.0,
      "red_name": "Patrick Kaase",
      "round": "2",
      "time": "2:30",
      "weight_class": "Middleweight"
    }
  ],
  "first_fight_date": "2006-10-12",
  "gender": "men",
  "history": [
    {
      "date": "2006-10-12",
      "fight_id": "756a4a1d70fe97cb",
      "rating": 1479.6,
      "scope": "division",
      "system": "men:Middleweight"
    },
    {
      "date": "2006-10-12",
      "fight_id": "756a4a1d70fe97cb",
      "rating": 1481.8,
      "scope": "overall",
      "system": "men:overall"
    }
  ],
  "instagram": null,
  "instagram_featured": false,
  "last_fight_date": "2006-10-12",
  "name": "Jarrod Kwitty",
  "nickname": "",
  "overall_elo": 1500.0,
  "peak_elo": 1500.0,
  "slug": "jarrod-kwitty",
  "systems": {
    "division": "men:Middleweight",
    "overall": "men:overall"
  },
  "weight_class": "Middleweight"
}
