{
  "activity_status": "inactive",
  "current_elo": 1556.2,
  "days_since_last_fight": 1106,
  "divisional_rank": 52,
  "fight_count": 31,
  "fight_log": [
    {
      "blue_name": "Jorge Masvidal",
      "bout_type": "Welterweight Bout",
      "date": "2023-04-08",
      "elo_delta": -17.9,
      "event_name": "UFC 287: Pereira vs. Adesanya 2",
      "fight_id": "9ebced314619c916",
      "gender": "men",
      "is_title": false,
      "method": "Decision - Unanimous",
      "opponent": "Gilbert Burns",
      "opponent_elo": 1614.9,
      "outcome": "red_win",
      "post_elo": 1594.6,
      "pre_elo": 1612.4,
      "red_name": "Gilbert Burns",
      "round": "3.0",
      "source": "https://raw.githubusercontent.com/komaksym/UFC-DataLab/main/data/stats/stats_processed_all_bouts.csv",
      "source_title": "",
      "time": "5:00",
      "weight_class": "Welterweight"
    },
    {
      "blue_name": "Jorge Masvidal",
      "bout_type": "Welterweight Bout",
      "date": "2022-03-05",
      "elo_delta": -16.6,
      "event_name": "UFC 272: Covington vs. Masvidal",
      "fight_id": "5059ccf03bacc268",
      "gender": "men",
      "is_title": false,
      "method": "Decision - Unanimous",
      "opponent": "Colby Covington",
      "opponent_elo": 1655.6,
      "outcome": "red_win",
      "post_elo": 1612.4,
      "pre_elo": 1629.1,
      "red_name": "Colby Covington",
      "round": "5.0",
      "source": "https://raw.githubusercontent.com/komaksym/UFC-DataLab/main/data/stats/stats_processed_all_bouts.csv",
      "source_title": "",
      "time": "5:00",
      "weight_class": "Welterweight"
    },
    {
      "blue_name": "Jorge Masvidal",
      "bout_type": "UFC Welterweight Title Bout",
      "date": "2021-04-24",
      "elo_delta": -15.9,
      "event_name": "UFC 261: Usman vs. Masvidal 2",
      "fight_id": "8ccc0eb21381c203",
      "gender": "men",
      "is_title": true,
      "method": "KO/TKO",
      "opponent": "Kamaru Usman",
      "opponent_elo": 1736.8,
      "outcome": "red_win",
      "post_elo": 1629.1,
      "pre_elo": 1644.9,
      "red_name": "Kamaru Usman",
      "round": "2.0",
      "source": "https://raw.githubusercontent.com/komaksym/UFC-DataLab/main/data/stats/stats_processed_all_bouts.csv",
      "source_title": "",
      "time": "1:02",
      "weight_class": "Welterweight"
    },
    {
      "blue_name": "Jorge Masvidal",
      "bout_type": "UFC Welterweight Title Bout",
      "date": "2020-07-11",
      "elo_delta": -17.4,
      "event_name": "UFC 251: Usman vs. Masvidal",
      "fight_id": "1bda8c2afed75496",
      "gender": "men",
      "is_title": true,
      "method": "Decision - Unanimous",
      "opponent": "Kamaru Usman",
      "opponent_elo": 1704.9,
      "outcome": "red_win",
      "post_elo": 1644.9,
      "pre_elo": 1662.3,
      "red_name": "Kamaru Usman",
      "round": "5.0",
      "source": "https://raw.githubusercontent.com/komaksym/UFC-DataLab/main/data/stats/stats_processed_all_bouts.csv",
      "source_title": "",
      "time": "5:00",
      "weight_class": "Welterweight"
    },
    {
      "blue_name": "Nate Diaz",
      "bout_type": "Welterweight Bout",
      "date": "2019-11-02",
      "elo_delta": 16.6,
      "event_name": "UFC 244: Masvidal vs. Diaz",
      "fight_id": "3d94f02778c2545e",
      "gender": "men",
      "is_title": false,
      "method": "TKO - Doctor's Stoppage",
      "opponent": "Nate Diaz",
      "opponent_elo": 1594.6,
      "outcome": "red_win",
      "post_elo": 1662.3,
      "pre_elo": 1645.7,
      "red_name": "Jorge Masvidal",
      "round": "3.0",
      "source": "https://raw.githubusercontent.com/komaksym/UFC-DataLab/main/data/stats/stats_processed_all_bouts.csv",
      "source_title": "",
      "time": "5:00",
      "weight_class": "Welterweight"
    },
    {
      "blue_name": "Ben Askren",
      "bout_type": "Welterweight Bout",
      "date": "2019-07-06",
      "elo_delta": 19.2,
      "event_name": "UFC 239: Jones vs. Santos",
      "fight_id": "aee0bc3f66d0f3fb",
      "gender": "men",
      "is_title": false,
      "method": "KO/TKO",
      "opponent": "Ben Askren",
      "opponent_elo": 1622.9,
      "outcome": "red_win",
      "post_elo": 1645.7,
      "pre_elo": 1626.5,
      "red_name": "Jorge Masvidal",
      "round": "1.0",
      "source": "https://raw.githubusercontent.com/komaksym/UFC-DataLab/main/data/stats/stats_processed_all_bouts.csv",
      "source_title": "",
      "time": "0:05",
      "weight_class": "Welterweight"
    },
    {
      "blue_name": "Jorge Masvidal",
      "bout_type": "Welterweight Bout",
      "date": "2019-03-16",
      "elo_delta": 18.1,
      "event_name": "UFC Fight Night: Till vs. Masvidal",
      "fight_id": "3743d948dba97e6b",
      "gender": "men",
      "is_title": false,
      "method": "KO/TKO",
      "opponent": "Darren Till",
      "opponent_elo": 1585.0,
      "outcome": "blue_win",
      "post_elo": 1626.5,
      "pre_elo": 1608.3,
      "red_name": "Darren Till",
      "round": "2.0",
      "source": "https://raw.githubusercontent.com/komaksym/UFC-DataLab/main/data/stats/stats_processed_all_bouts.csv",
      "source_title": "",
      "time": "3:05",
      "weight_class": "Welterweight"
    },
    {
      "blue_name": "Jorge Masvidal",
      "bout_type": "Welterweight Bout",
      "date": "2017-11-04",
      "elo_delta": -18.5,
      "event_name": "UFC 217: Bisping vs. St-Pierre",
      "fight_id": "1cf6c6656769de97",
      "gender": "men",
      "is_title": false,
      "method": "Decision - Unanimous",
      "opponent": "Stephen Thompson",
      "opponent_elo": 1617.8,
      "outcome": "red_win",
      "post_elo": 1608.3,
      "pre_elo": 1626.8,
      "red_name": "Stephen Thompson",
      "round": "3.0",
      "source": "https://raw.githubusercontent.com/komaksym/UFC-DataLab/main/data/stats/stats_processed_all_bouts.csv",
      "source_title": "",
      "time": "5:00",
      "weight_class": "Welterweight"
    },
    {
      "blue_name": "Jorge Masvidal",
      "bout_type": "Welterweight Bout",
      "date": "2017-05-13",
      "elo_delta": -15.6,
      "event_name": "UFC 211: Miocic vs. Dos Santos",
      "fight_id": "167e6a8799d26baa",
      "gender": "men",
      "is_title": false,
      "method": "Decision - Split",
      "opponent": "Demian Maia",
      "opponent_elo": 1688.5,
      "outcome": "red_win",
      "post_elo": 1626.8,
      "pre_elo": 1642.4,
      "red_name": "Demian Maia",
      "round": "3.0",
      "source": "https://raw.githubusercontent.com/komaksym/UFC-DataLab/main/data/stats/stats_processed_all_bouts.csv",
      "source_title": "",
      "time": "5:00",
      "weight_class": "Welterweight"
    },
    {
      "blue_name": "Jorge Masvidal",
      "bout_type": "Welterweight Bout",
      "date": "2017-01-28",
      "elo_delta": 26.3,
      "event_name": "UFC on FOX: Shevchenko vs. Pena",
      "fight_id": "072a17963e538e9a",
      "gender": "men",
      "is_title": false,
      "method": "KO/TKO",
      "opponent": "Donald Cerrone",
      "opponent_elo": 1744.1,
      "outcome": "blue_win",
      "post_elo": 1642.4,
      "pre_elo": 1616.1,
      "red_name": "Donald Cerrone",
      "round": "2.0",
      "source": "https://raw.githubusercontent.com/komaksym/UFC-DataLab/main/data/stats/stats_processed_all_bouts.csv",
      "source_title": "",
      "time": "1:00",
      "weight_class": "Welterweight"
    },
    {
      "blue_name": "Jorge Masvidal",
      "bout_type": "Welterweight Bout",
      "date": "2016-12-03",
      "elo_delta": 18.1,
      "event_name": "The Ultimate Fighter: Tournament of Champions Finale",
      "fight_id": "7094785fa2750db0",
      "gender": "men",
      "is_title": false,
      "method": "KO/TKO",
      "opponent": "Jake Ellenberger",
      "opponent_elo": 1573.2,
      "outcome": "blue_win",
      "post_elo": 1616.1,
      "pre_elo": 1598.1,
      "red_name": "Jake Ellenberger",
      "round": "1.0",
      "source": "https://raw.githubusercontent.com/komaksym/UFC-DataLab/main/data/stats/stats_processed_all_bouts.csv",
      "source_title": "",
      "time": "4:05",
      "weight_class": "Welterweight"
    },
    {
      "blue_name": "Jorge Masvidal",
      "bout_type": "Welterweight Bout",
      "date": "2016-07-30",
      "elo_delta": 16.0,
      "event_name": "UFC 201: Lawler vs. Woodley",
      "fight_id": "792a8dabb3fa2dc8",
      "gender": "men",
      "is_title": false,
      "method": "Decision - Unanimous",
      "opponent": "Ross Pearson",
      "opponent_elo": 1543.1,
      "outcome": "blue_win",
      "post_elo": 1598.1,
      "pre_elo": 1582.1,
      "red_name": "Ross Pearson",
      "round": "3.0",
      "source": "https://raw.githubusercontent.com/komaksym/UFC-DataLab/main/data/stats/stats_processed_all_bouts.csv",
      "source_title": "",
      "time": "5:00",
      "weight_class": "Welterweight"
    },
    {
      "blue_name": "Lorenz Larkin",
      "bout_type": "Welterweight Bout",
      "date": "2016-05-29",
      "elo_delta": -23.1,
      "event_name": "UFC Fight Night: Almeida vs Garbrandt",
      "fight_id": "db2023d671253512",
      "gender": "men",
      "is_title": false,
      "method": "Decision - Split",
      "opponent": "Lorenz Larkin",
      "opponent_elo": 1503.6,
      "outcome": "blue_win",
      "post_elo": 1582.1,
      "pre_elo": 1605.2,
      "red_name": "Jorge Masvidal",
      "round": "3.0",
      "source": "https://raw.githubusercontent.com/komaksym/UFC-DataLab/main/data/stats/stats_processed_all_bouts.csv",
      "source_title": "",
      "time": "5:00",
      "weight_class": "Welterweight"
    },
    {
      "blue_name": "Jorge Masvidal",
      "bout_type": "Welterweight Bout",
      "date": "2015-11-28",
      "elo_delta": -15.5,
      "event_name": "UFC Fight Night: Henderson vs Masvidal",
      "fight_id": "1c31940fb55332c2",
      "gender": "men",
      "is_title": false,
      "method": "Decision - Split",
      "opponent": "Benson Henderson",
      "opponent_elo": 1668.5,
      "outcome": "red_win",
      "post_elo": 1605.2,
      "pre_elo": 1620.7,
      "red_name": "Benson Henderson",
      "round": "5.0",
      "source": "https://raw.githubusercontent.com/komaksym/UFC-DataLab/main/data/stats/stats_processed_all_bouts.csv",
      "source_title": "",
      "time": "5:00",
      "weight_class": "Welterweight"
    },
    {
      "blue_name": "Cezar Ferreira",
      "bout_type": "Welterweight Bout",
      "date": "2015-07-12",
      "elo_delta": 15.1,
      "event_name": "The Ultimate Fighter: American Top Team vs. Blackzilians Finale",
      "fight_id": "5487eb1c579f4bbe",
      "gender": "men",
      "is_title": false,
      "method": "KO/TKO",
      "opponent": "Cezar Ferreira",
      "opponent_elo": 1526.2,
      "outcome": "red_win",
      "post_elo": 1620.7,
      "pre_elo": 1605.7,
      "red_name": "Jorge Masvidal",
      "round": "1.0",
      "source": "https://raw.githubusercontent.com/komaksym/UFC-DataLab/main/data/stats/stats_processed_all_bouts.csv",
      "source_title": "",
      "time": "4:22",
      "weight_class": "Welterweight"
    },
    {
      "blue_name": "Al Iaquinta",
      "bout_type": "Lightweight Bout",
      "date": "2015-04-04",
      "elo_delta": -21.1,
      "event_name": "UFC Fight Night: Mendes vs Lamas",
      "fight_id": "db75b6deff7780c5",
      "gender": "men",
      "is_title": false,
      "method": "Decision - Split",
      "opponent": "Al Iaquinta",
      "opponent_elo": 1576.1,
      "outcome": "blue_win",
      "post_elo": 1614.7,
      "pre_elo": 1635.7,
      "red_name": "Jorge Masvidal",
      "round": "3.0",
      "source": "https://raw.githubusercontent.com/komaksym/UFC-DataLab/main/data/stats/stats_processed_all_bouts.csv",
      "source_title": "",
      "time": "5:00",
      "weight_class": "Lightweight"
    },
    {
      "blue_name": "James Krause",
      "bout_type": "Lightweight Bout",
      "date": "2014-09-27",
      "elo_delta": 10.8,
      "event_name": "UFC 178: Johnson vs Cariaso",
      "fight_id": "6106548067fdb6af",
      "gender": "men",
      "is_title": false,
      "method": "Decision - Unanimous",
      "opponent": "James Krause",
      "opponent_elo": 1478.6,
      "outcome": "red_win",
      "post_elo": 1635.7,
      "pre_elo": 1624.9,
      "red_name": "Jorge Masvidal",
      "round": "3.0",
      "source": "https://raw.githubusercontent.com/komaksym/UFC-DataLab/main/data/stats/stats_processed_all_bouts.csv",
      "source_title": "",
      "time": "5:00",
      "weight_class": "Lightweight"
    },
    {
      "blue_name": "Jorge Masvidal",
      "bout_type": "Lightweight Bout",
      "date": "2014-07-26",
      "elo_delta": 15.0,
      "event_name": "UFC on FOX: Lawler vs Brown",
      "fight_id": "794557cef1de901d",
      "gender": "men",
      "is_title": false,
      "method": "Decision - Unanimous",
      "opponent": "Daron Cruickshank",
      "opponent_elo": 1552.3,
      "outcome": "blue_win",
      "post_elo": 1624.9,
      "pre_elo": 1609.8,
      "red_name": "Daron Cruickshank",
      "round": "3.0",
      "source": "https://raw.githubusercontent.com/komaksym/UFC-DataLab/main/data/stats/stats_processed_all_bouts.csv",
      "source_title": "",
      "time": "5:00",
      "weight_class": "Lightweight"
    },
    {
      "blue_name": "Pat Healy",
      "bout_type": "Lightweight Bout",
      "date": "2014-04-19",
      "elo_delta": 13.9,
      "event_name": "UFC on FOX: Werdum vs Browne",
      "fight_id": "16809a730ccab16d",
      "gender": "men",
      "is_title": false,
      "method": "Decision - Unanimous",
      "opponent": "Pat Healy",
      "opponent_elo": 1515.6,
      "outcome": "red_win",
      "post_elo": 1609.8,
      "pre_elo": 1595.9,
      "red_name": "Jorge Masvidal",
      "round": "3.0",
      "source": "https://raw.githubusercontent.com/komaksym/UFC-DataLab/main/data/stats/stats_processed_all_bouts.csv",
      "source_title": "",
      "time": "5:00",
      "weight_class": "Lightweight"
    },
    {
      "blue_name": "Rustam Khabilov",
      "bout_type": "Lightweight Bout",
      "date": "2013-11-06",
      "elo_delta": -22.0,
      "event_name": "UFC Fight Night: Fight for the Troops 3",
      "fight_id": "250b4509dd8197af",
      "gender": "men",
      "is_title": false,
      "method": "Decision - Unanimous",
      "opponent": "Rustam Khabilov",
      "opponent_elo": 1538.7,
      "outcome": "blue_win",
      "post_elo": 1595.9,
      "pre_elo": 1618.0,
      "red_name": "Jorge Masvidal",
      "round": "3.0",
      "source": "https://raw.githubusercontent.com/komaksym/UFC-DataLab/main/data/stats/stats_processed_all_bouts.csv",
      "source_title": "",
      "time": "5:00",
      "weight_class": "Lightweight"
    },
    {
      "blue_name": "Jorge Masvidal",
      "bout_type": "Lightweight Bout",
      "date": "2013-07-27",
      "elo_delta": 15.9,
      "event_name": "UFC on FOX: Johnson vs Moraga",
      "fight_id": "24ec1aaaeeaceff0",
      "gender": "men",
      "is_title": false,
      "method": "Submission",
      "opponent": "Michael Chiesa",
      "opponent_elo": 1537.8,
      "outcome": "blue_win",
      "post_elo": 1618.0,
      "pre_elo": 1602.1,
      "red_name": "Michael Chiesa",
      "round": "2.0",
      "source": "https://raw.githubusercontent.com/komaksym/UFC-DataLab/main/data/stats/stats_processed_all_bouts.csv",
      "source_title": "",
      "time": "4:59",
      "weight_class": "Lightweight"
    },
    {
      "blue_name": "Jorge Masvidal",
      "bout_type": "Lightweight Bout",
      "date": "2013-04-20",
      "elo_delta": 15.5,
      "event_name": "UFC on FOX: Henderson vs Melendez",
      "fight_id": "289b20bb6bbe4362",
      "gender": "men",
      "is_title": false,
      "method": "Decision - Unanimous",
      "opponent": "Tim Means",
      "opponent_elo": 1537.4,
      "outcome": "blue_win",
      "post_elo": 1602.1,
      "pre_elo": 1586.6,
      "red_name": "Tim Means",
      "round": "3.0",
      "source": "https://raw.githubusercontent.com/komaksym/UFC-DataLab/main/data/stats/stats_processed_all_bouts.csv",
      "source_title": "",
      "time": "5:00",
      "weight_class": "Lightweight"
    },
    {
      "blue_name": "Justin Wilcox",
      "bout_type": "Lightweight Bout",
      "date": "2012-07-14",
      "elo_delta": 14.6,
      "event_name": "Strikeforce: Rockhold vs. Kennedy",
      "fight_id": "c147fa2166d29d37",
      "gender": "men",
      "is_title": false,
      "method": "Decision (split) (29–28, 28–29, 30–27)",
      "opponent": "Justin Wilcox",
      "opponent_elo": 1506.0,
      "outcome": "red_win",
      "post_elo": 1586.6,
      "pre_elo": 1572.0,
      "red_name": "Jorge Masvidal",
      "round": "3",
      "source": "manual",
      "source_title": "Strikeforce: Rockhold vs. Kennedy",
      "time": "5:00",
      "weight_class": "Lightweight"
    },
    {
      "blue_name": "Jorge Masvidal",
      "bout_type": "Lightweight Bout",
      "date": "2011-12-17",
      "elo_delta": -11.7,
      "event_name": "Strikeforce: Melendez vs. Masvidal",
      "fight_id": "4171ae4234d73bb7",
      "gender": "men",
      "is_title": false,
      "method": "Decision (unanimous) (50–45, 50–45, 49–46)",
      "opponent": "Gilbert Melendez",
      "opponent_elo": 1710.1,
      "outcome": "red_win",
      "post_elo": 1572.0,
      "pre_elo": 1583.7,
      "red_name": "Gilbert Melendez",
      "round": "5",
      "source": "manual",
      "source_title": "Strikeforce: Melendez vs. Masvidal",
      "time": "5:00",
      "weight_class": "Lightweight"
    },
    {
      "blue_name": "K. J. Noons",
      "bout_type": "Lightweight Bout",
      "date": "2011-06-18",
      "elo_delta": 17.0,
      "event_name": "Strikeforce: Overeem vs. Werdum",
      "fight_id": "01b8a0aa318b60ef",
      "gender": "men",
      "is_title": false,
      "method": "Decision (unanimous) (30–27, 30–27, 30–27)",
      "opponent": "K. J. Noons",
      "opponent_elo": 1547.0,
      "outcome": "red_win",
      "post_elo": 1583.7,
      "pre_elo": 1566.7,
      "red_name": "Jorge Masvidal",
      "round": "3",
      "source": "manual",
      "source_title": "Strikeforce: Overeem vs. Werdum",
      "time": "5:00",
      "weight_class": "Lightweight"
    },
    {
      "blue_name": "Billy Evangelista",
      "bout_type": "Lightweight Bout",
      "date": "2011-03-05",
      "elo_delta": 20.5,
      "event_name": "Strikeforce: Feijao vs. Henderson",
      "fight_id": "d2d43bd48486552f",
      "gender": "men",
      "is_title": false,
      "method": "Decision (unanimous) (30–27, 30–27, 30–27)",
      "opponent": "Billy Evangelista",
      "opponent_elo": 1594.3,
      "outcome": "red_win",
      "post_elo": 1566.7,
      "pre_elo": 1546.3,
      "red_name": "Jorge Masvidal",
      "round": "3",
      "source": "manual",
      "source_title": "Strikeforce: Feijao vs. Henderson",
      "time": "5:00",
      "weight_class": "Lightweight"
    },
    {
      "blue_name": "Eric Reynolds",
      "bout_type": "Lightweight Bout",
      "date": "2009-06-19",
      "elo_delta": 18.1,
      "event_name": "Bellator 12",
      "fight_id": "0774eafefee5f941",
      "gender": "men",
      "is_title": false,
      "method": "Submission (rear-naked choke)",
      "opponent": "Eric Reynolds",
      "opponent_elo": 1504.4,
      "outcome": "red_win",
      "post_elo": 1546.3,
      "pre_elo": 1528.2,
      "red_name": "Jorge Masvidal",
      "round": "3",
      "source": "manual",
      "source_title": "Bellator 12",
      "time": "3:33",
      "weight_class": "Lightweight"
    },
    {
      "blue_name": "Jorge Masvidal",
      "bout_type": "Lightweight Bout",
      "date": "2009-05-01",
      "elo_delta": -22.1,
      "event_name": "Bellator 5",
      "fight_id": "36590172820e2f3f",
      "gender": "men",
      "is_title": false,
      "method": "Technical Submission (inverted-triangle choke)",
      "opponent": "Toby Imada",
      "opponent_elo": 1503.1,
      "outcome": "red_win",
      "post_elo": 1528.2,
      "pre_elo": 1550.2,
      "red_name": "Toby Imada",
      "round": "3",
      "source": "manual",
      "source_title": "Bellator 5",
      "time": "3:22",
      "weight_class": "Lightweight"
    },
    {
      "blue_name": "Nick Agallar",
      "bout_type": "Lightweight Bout",
      "date": "2009-04-03",
      "elo_delta": 16.6,
      "event_name": "Bellator 1",
      "fight_id": "44deb43533e392e2",
      "gender": "men",
      "is_title": false,
      "method": "TKO (punches)",
      "opponent": "Nick Agallar",
      "opponent_elo": 1481.8,
      "outcome": "red_win",
      "post_elo": 1550.2,
      "pre_elo": 1533.6,
      "red_name": "Jorge Masvidal",
      "round": "1",
      "source": "manual",
      "source_title": "Bellator 1",
      "time": "1:19",
      "weight_class": "Lightweight"
    },
    {
      "blue_name": "Ryan Healy",
      "bout_type": "Lightweight Bout",
      "date": "2008-02-23",
      "elo_delta": 16.4,
      "event_name": "Strikeforce: At The Dome",
      "fight_id": "dfe788dc9d01a481",
      "gender": "men",
      "is_title": false,
      "method": "Decision (unanimous)",
      "opponent": "Ryan Healy",
      "opponent_elo": 1485.7,
      "outcome": "red_win",
      "post_elo": 1533.6,
      "pre_elo": 1517.3,
      "red_name": "Jorge Masvidal",
      "round": "3",
      "source": "manual",
      "source_title": "Strikeforce: At The Dome",
      "time": "5:00",
      "weight_class": "Lightweight"
    }
  ],
  "first_fight_date": "2007-09-29",
  "gender": "men",
  "history": [
    {
      "date": "2007-09-29",
      "fight_id": "ea87ea1fb3bbdef4",
      "rating": 1517.3,
      "scope": "overall",
      "system": "men:overall"
    },
    {
      "date": "2008-02-23",
      "fight_id": "dfe788dc9d01a481",
      "rating": 1533.6,
      "scope": "division",
      "system": "men:Lightweight"
    },
    {
      "date": "2008-02-23",
      "fight_id": "dfe788dc9d01a481",
      "rating": 1531.8,
      "scope": "overall",
      "system": "men:overall"
    },
    {
      "date": "2009-04-03",
      "fight_id": "44deb43533e392e2",
      "rating": 1550.2,
      "scope": "division",
      "system": "men:Lightweight"
    },
    {
      "date": "2009-04-03",
      "fight_id": "44deb43533e392e2",
      "rating": 1546.7,
      "scope": "overall",
      "system": "men:overall"
    },
    {
      "date": "2009-05-01",
      "fight_id": "36590172820e2f3f",
      "rating": 1528.2,
      "scope": "division",
      "system": "men:Lightweight"
    },
    {
      "date": "2009-05-01",
      "fight_id": "36590172820e2f3f",
      "rating": 1527.1,
      "scope": "overall",
      "system": "men:overall"
    },
    {
      "date": "2009-06-19",
      "fight_id": "0774eafefee5f941",
      "rating": 1546.3,
      "scope": "division",
      "system": "men:Lightweight"
    },
    {
      "date": "2009-06-19",
      "fight_id": "0774eafefee5f941",
      "rating": 1543.3,
      "scope": "overall",
      "system": "men:overall"
    },
    {
      "date": "2011-03-05",
      "fight_id": "d2d43bd48486552f",
      "rating": 1566.7,
      "scope": "division",
      "system": "men:Lightweight"
    },
    {
      "date": "2011-03-05",
      "fight_id": "d2d43bd48486552f",
      "rating": 1561.2,
      "scope": "overall",
      "system": "men:overall"
    },
    {
      "date": "2011-06-18",
      "fight_id": "01b8a0aa318b60ef",
      "rating": 1583.7,
      "scope": "division",
      "system": "men:Lightweight"
    },
    {
      "date": "2011-06-18",
      "fight_id": "01b8a0aa318b60ef",
      "rating": 1576.0,
      "scope": "overall",
      "system": "men:overall"
    },
    {
      "date": "2011-12-17",
      "fight_id": "4171ae4234d73bb7",
      "rating": 1572.0,
      "scope": "division",
      "system": "men:Lightweight"
    },
    {
      "date": "2011-12-17",
      "fight_id": "4171ae4234d73bb7",
      "rating": 1565.8,
      "scope": "overall",
      "system": "men:overall"
    },
    {
      "date": "2012-07-14",
      "fight_id": "c147fa2166d29d37",
      "rating": 1586.6,
      "scope": "division",
      "system": "men:Lightweight"
    },
    {
      "date": "2012-07-14",
      "fight_id": "c147fa2166d29d37",
      "rating": 1579.0,
      "scope": "overall",
      "system": "men:overall"
    },
    {
      "date": "2013-04-20",
      "fight_id": "289b20bb6bbe4362",
      "rating": 1602.1,
      "scope": "division",
      "system": "men:Lightweight"
    },
    {
      "date": "2013-04-20",
      "fight_id": "289b20bb6bbe4362",
      "rating": 1593.0,
      "scope": "overall",
      "system": "men:overall"
    },
    {
      "date": "2013-07-27",
      "fight_id": "24ec1aaaeeaceff0",
      "rating": 1618.0,
      "scope": "division",
      "system": "men:Lightweight"
    },
    {
      "date": "2013-07-27",
      "fight_id": "24ec1aaaeeaceff0",
      "rating": 1607.3,
      "scope": "overall",
      "system": "men:overall"
    },
    {
      "date": "2013-11-06",
      "fight_id": "250b4509dd8197af",
      "rating": 1595.9,
      "scope": "division",
      "system": "men:Lightweight"
    },
    {
      "date": "2013-11-06",
      "fight_id": "250b4509dd8197af",
      "rating": 1588.0,
      "scope": "overall",
      "system": "men:overall"
    },
    {
      "date": "2014-04-19",
      "fight_id": "16809a730ccab16d",
      "rating": 1609.8,
      "scope": "division",
      "system": "men:Lightweight"
    },
    {
      "date": "2014-04-19",
      "fight_id": "16809a730ccab16d",
      "rating": 1600.6,
      "scope": "overall",
      "system": "men:overall"
    },
    {
      "date": "2014-07-26",
      "fight_id": "794557cef1de901d",
      "rating": 1624.9,
      "scope": "division",
      "system": "men:Lightweight"
    },
    {
      "date": "2014-07-26",
      "fight_id": "794557cef1de901d",
      "rating": 1614.1,
      "scope": "overall",
      "system": "men:overall"
    },
    {
      "date": "2014-09-27",
      "fight_id": "6106548067fdb6af",
      "rating": 1635.7,
      "scope": "division",
      "system": "men:Lightweight"
    },
    {
      "date": "2014-09-27",
      "fight_id": "6106548067fdb6af",
      "rating": 1624.2,
      "scope": "overall",
      "system": "men:overall"
    },
    {
      "date": "2015-04-04",
      "fight_id": "db75b6deff7780c5",
      "rating": 1614.7,
      "scope": "division",
      "system": "men:Lightweight"
    },
    {
      "date": "2015-04-04",
      "fight_id": "db75b6deff7780c5",
      "rating": 1605.7,
      "scope": "overall",
      "system": "men:overall"
    },
    {
      "date": "2015-07-12",
      "fight_id": "5487eb1c579f4bbe",
      "rating": 1620.7,
      "scope": "division",
      "system": "men:Welterweight"
    },
    {
      "date": "2015-07-12",
      "fight_id": "5487eb1c579f4bbe",
      "rating": 1619.1,
      "scope": "overall",
      "system": "men:overall"
    },
    {
      "date": "2015-11-28",
      "fight_id": "1c31940fb55332c2",
      "rating": 1605.2,
      "scope": "division",
      "system": "men:Welterweight"
    },
    {
      "date": "2015-11-28",
      "fight_id": "1c31940fb55332c2",
      "rating": 1605.3,
      "scope": "overall",
      "system": "men:overall"
    },
    {
      "date": "2016-05-29",
      "fight_id": "db2023d671253512",
      "rating": 1582.1,
      "scope": "division",
      "system": "men:Welterweight"
    },
    {
      "date": "2016-05-29",
      "fight_id": "db2023d671253512",
      "rating": 1584.6,
      "scope": "overall",
      "system": "men:overall"
    },
    {
      "date": "2016-07-30",
      "fight_id": "792a8dabb3fa2dc8",
      "rating": 1598.1,
      "scope": "division",
      "system": "men:Welterweight"
    },
    {
      "date": "2016-07-30",
      "fight_id": "792a8dabb3fa2dc8",
      "rating": 1598.7,
      "scope": "overall",
      "system": "men:overall"
    },
    {
      "date": "2016-12-03",
      "fight_id": "7094785fa2750db0",
      "rating": 1616.1,
      "scope": "division",
      "system": "men:Welterweight"
    },
    {
      "date": "2016-12-03",
      "fight_id": "7094785fa2750db0",
      "rating": 1614.5,
      "scope": "overall",
      "system": "men:overall"
    },
    {
      "date": "2017-01-28",
      "fight_id": "072a17963e538e9a",
      "rating": 1642.4,
      "scope": "division",
      "system": "men:Welterweight"
    },
    {
      "date": "2017-01-28",
      "fight_id": "072a17963e538e9a",
      "rating": 1637.7,
      "scope": "overall",
      "system": "men:overall"
    },
    {
      "date": "2017-05-13",
      "fight_id": "167e6a8799d26baa",
      "rating": 1626.8,
      "scope": "division",
      "system": "men:Welterweight"
    },
    {
      "date": "2017-05-13",
      "fight_id": "167e6a8799d26baa",
      "rating": 1623.4,
      "scope": "overall",
      "system": "men:overall"
    },
    {
      "date": "2017-11-04",
      "fight_id": "1cf6c6656769de97",
      "rating": 1608.3,
      "scope": "division",
      "system": "men:Welterweight"
    },
    {
      "date": "2017-11-04",
      "fight_id": "1cf6c6656769de97",
      "rating": 1606.6,
      "scope": "overall",
      "system": "men:overall"
    },
    {
      "date": "2019-03-16",
      "fight_id": "3743d948dba97e6b",
      "rating": 1626.5,
      "scope": "division",
      "system": "men:Welterweight"
    },
    {
      "date": "2019-03-16",
      "fight_id": "3743d948dba97e6b",
      "rating": 1622.3,
      "scope": "overall",
      "system": "men:overall"
    },
    {
      "date": "2019-07-06",
      "fight_id": "aee0bc3f66d0f3fb",
      "rating": 1645.7,
      "scope": "division",
      "system": "men:Welterweight"
    },
    {
      "date": "2019-07-06",
      "fight_id": "aee0bc3f66d0f3fb",
      "rating": 1639.0,
      "scope": "overall",
      "system": "men:overall"
    },
    {
      "date": "2019-11-02",
      "fight_id": "3d94f02778c2545e",
      "rating": 1662.3,
      "scope": "division",
      "system": "men:Welterweight"
    },
    {
      "date": "2019-11-02",
      "fight_id": "3d94f02778c2545e",
      "rating": 1655.8,
      "scope": "overall",
      "system": "men:overall"
    },
    {
      "date": "2020-07-11",
      "fight_id": "1bda8c2afed75496",
      "rating": 1644.9,
      "scope": "division",
      "system": "men:Welterweight"
    },
    {
      "date": "2020-07-11",
      "fight_id": "1bda8c2afed75496",
      "rating": 1639.6,
      "scope": "overall",
      "system": "men:overall"
    },
    {
      "date": "2021-04-24",
      "fight_id": "8ccc0eb21381c203",
      "rating": 1629.1,
      "scope": "division",
      "system": "men:Welterweight"
    },
    {
      "date": "2021-04-24",
      "fight_id": "8ccc0eb21381c203",
      "rating": 1624.7,
      "scope": "overall",
      "system": "men:overall"
    },
    {
      "date": "2022-03-05",
      "fight_id": "5059ccf03bacc268",
      "rating": 1612.4,
      "scope": "division",
      "system": "men:Welterweight"
    },
    {
      "date": "2022-03-05",
      "fight_id": "5059ccf03bacc268",
      "rating": 1609.4,
      "scope": "overall",
      "system": "men:overall"
    },
    {
      "date": "2023-04-08",
      "fight_id": "9ebced314619c916",
      "rating": 1594.6,
      "scope": "division",
      "system": "men:Welterweight"
    },
    {
      "date": "2023-04-08",
      "fight_id": "9ebced314619c916",
      "rating": 1594.9,
      "scope": "overall",
      "system": "men:overall"
    }
  ],
  "inactive_after_days": 545,
  "inactivity_adjusted": true,
  "instagram": null,
  "instagram_featured": false,
  "last_fight_date": "2023-04-08",
  "name": "Jorge Masvidal",
  "nickname": "",
  "overall_elo": 1556.5,
  "peak_elo": 1662.3,
  "raw_current_elo": 1594.6,
  "raw_overall_elo": 1594.9,
  "slug": "jorge-masvidal",
  "systems": {
    "division": "men:Welterweight",
    "overall": "men:overall"
  },
  "weight_class": "Welterweight"
}
