{
  "activity_status": "inactive",
  "current_elo": 1500.0,
  "days_since_last_fight": 1155,
  "divisional_rank": 431,
  "fight_count": 1,
  "fight_log": [
    {
      "blue_name": "Ko Kyung-jin",
      "bout_type": "Middleweight 84 kg Bout",
      "date": "2023-02-25",
      "elo_delta": 19.4,
      "event_name": "Road FC 63",
      "fight_id": "492c80faf2dbfebc",
      "gender": "men",
      "is_title": false,
      "method": "TKO (Punches)",
      "opponent": "Ko Kyung-jin",
      "opponent_elo": 1500.0,
      "outcome": "red_win",
      "post_elo": 1519.4,
      "pre_elo": 1500.0,
      "red_name": "Jung Seung-ho",
      "round": "1",
      "source": "manual",
      "source_title": "2023 in Road FC",
      "time": "2:53",
      "weight_class": "Middleweight"
    }
  ],
  "first_fight_date": "2023-02-25",
  "gender": "men",
  "history": [
    {
      "date": "2023-02-25",
      "fight_id": "492c80faf2dbfebc",
      "rating": 1519.4,
      "scope": "division",
      "system": "men:Middleweight"
    },
    {
      "date": "2023-02-25",
      "fight_id": "492c80faf2dbfebc",
      "rating": 1517.3,
      "scope": "overall",
      "system": "men:overall"
    }
  ],
  "inactive_after_days": 545,
  "inactivity_adjusted": true,
  "instagram": null,
  "instagram_featured": false,
  "last_fight_date": "2023-02-25",
  "name": "Jung Seung-ho",
  "nickname": "",
  "overall_elo": 1500.0,
  "peak_elo": 1519.4,
  "raw_current_elo": 1519.4,
  "raw_overall_elo": 1517.3,
  "slug": "jung-seung-ho",
  "systems": {
    "division": "men:Middleweight",
    "overall": "men:overall"
  },
  "weight_class": "Middleweight"
}
