{
  "current_elo": 1500.0,
  "divisional_rank": 605,
  "fight_count": 1,
  "fight_log": [
    {
      "blue_name": "Jeff Savoy",
      "bout_type": "Open Weight Bout",
      "date": "2008-03-29",
      "elo_delta": 19.4,
      "event_name": "Cage Warriors: USA Battle Royale",
      "fight_id": "289303ed4c023068",
      "gender": "men",
      "is_title": false,
      "method": "Submission (Toe Hold)",
      "opponent": "Jeff Savoy",
      "opponent_elo": 1500.0,
      "outcome": "red_win",
      "post_elo": 1519.4,
      "pre_elo": 1500.0,
      "red_name": "Justin Flood",
      "round": "1",
      "time": "2:17",
      "weight_class": "Open Weight"
    }
  ],
  "first_fight_date": "2008-03-29",
  "gender": "men",
  "history": [
    {
      "date": "2008-03-29",
      "fight_id": "289303ed4c023068",
      "rating": 1519.4,
      "scope": "division",
      "system": "men:Open Weight"
    },
    {
      "date": "2008-03-29",
      "fight_id": "289303ed4c023068",
      "rating": 1517.3,
      "scope": "overall",
      "system": "men:overall"
    }
  ],
  "instagram": null,
  "instagram_featured": false,
  "last_fight_date": "2008-03-29",
  "name": "Justin Flood",
  "nickname": "",
  "overall_elo": 1500.0,
  "peak_elo": 1519.4,
  "slug": "justin-flood",
  "systems": {
    "division": "men:Open Weight",
    "overall": "men:overall"
  },
  "weight_class": "Open Weight"
}
