{
  "activity_status": "inactive",
  "current_elo": 1500.0,
  "days_since_last_fight": 3788,
  "divisional_rank": 535,
  "fight_count": 2,
  "fight_log": [
    {
      "blue_name": "Konstantin Erokhin",
      "bout_type": "Heavyweight Bout",
      "date": "2015-12-11",
      "elo_delta": -16.0,
      "event_name": "The Ultimate Fighter: Team McGregor vs. Team Faber Finale",
      "fight_id": "f3066cebeaae8afb",
      "gender": "men",
      "is_title": false,
      "method": "Decision - Unanimous",
      "opponent": "Gabriel Gonzaga",
      "opponent_elo": 1519.8,
      "outcome": "red_win",
      "post_elo": 1465.1,
      "pre_elo": 1481.1,
      "red_name": "Gabriel Gonzaga",
      "round": "3.0",
      "source": "https://raw.githubusercontent.com/komaksym/UFC-DataLab/main/data/stats/stats_processed_all_bouts.csv",
      "source_title": "",
      "time": "5:00",
      "weight_class": "Heavyweight"
    },
    {
      "blue_name": "Konstantin Erokhin",
      "bout_type": "Heavyweight Bout",
      "date": "2015-01-24",
      "elo_delta": -18.9,
      "event_name": "UFC on FOX: Gustafsson vs Johnson",
      "fight_id": "c0c939f7582b666e",
      "gender": "men",
      "is_title": false,
      "method": "Decision - Unanimous",
      "opponent": "Viktor Pesta",
      "opponent_elo": 1482.0,
      "outcome": "red_win",
      "post_elo": 1481.1,
      "pre_elo": 1500.0,
      "red_name": "Viktor Pesta",
      "round": "3.0",
      "source": "https://raw.githubusercontent.com/komaksym/UFC-DataLab/main/data/stats/stats_processed_all_bouts.csv",
      "source_title": "",
      "time": "5:00",
      "weight_class": "Heavyweight"
    }
  ],
  "first_fight_date": "2015-01-24",
  "gender": "men",
  "history": [
    {
      "date": "2015-01-24",
      "fight_id": "c0c939f7582b666e",
      "rating": 1481.1,
      "scope": "division",
      "system": "men:Heavyweight"
    },
    {
      "date": "2015-01-24",
      "fight_id": "c0c939f7582b666e",
      "rating": 1483.3,
      "scope": "overall",
      "system": "men:overall"
    },
    {
      "date": "2015-12-11",
      "fight_id": "f3066cebeaae8afb",
      "rating": 1465.1,
      "scope": "division",
      "system": "men:Heavyweight"
    },
    {
      "date": "2015-12-11",
      "fight_id": "f3066cebeaae8afb",
      "rating": 1468.9,
      "scope": "overall",
      "system": "men:overall"
    }
  ],
  "inactive_after_days": 545,
  "inactivity_adjusted": true,
  "instagram": null,
  "instagram_featured": false,
  "last_fight_date": "2015-12-11",
  "name": "Konstantin Erokhin",
  "nickname": "",
  "overall_elo": 1500.0,
  "peak_elo": 1500.0,
  "raw_current_elo": 1465.1,
  "raw_overall_elo": 1468.9,
  "slug": "konstantin-erokhin",
  "systems": {
    "division": "men:Heavyweight",
    "overall": "men:overall"
  },
  "weight_class": "Heavyweight"
}
