{
  "current_elo": 1500.0,
  "divisional_rank": null,
  "fight_count": 1,
  "fight_log": [],
  "first_fight_date": "2020-12-31",
  "gender": "men",
  "history": [
    {
      "date": "2020-12-31",
      "fight_id": "30c93a6cda73a9b6",
      "rating": 1490.7,
      "scope": "overall",
      "system": "men:overall"
    }
  ],
  "inactivity_adjusted": true,
  "instagram": null,
  "instagram_featured": false,
  "last_fight_date": "2020-12-31",
  "name": "Kumandoi Petcharoenvit",
  "nickname": "",
  "overall_elo": 1500.0,
  "peak_elo": 1500.0,
  "raw_current_elo": 1490.7,
  "raw_overall_elo": 1490.7,
  "slug": "kumandoi-petcharoenvit",
  "systems": {
    "division": "men:Catch Weight",
    "overall": "men:overall"
  },
  "weight_class": "Catch Weight"
}
