{
  "current_elo": 1481.8,
  "divisional_rank": 1419,
  "fight_count": 1,
  "fight_log": [
    {
      "blue_name": "Nikolay Kiosse",
      "bout_type": "Lightweight Bout",
      "date": "2026-02-06",
      "elo_delta": -18.2,
      "event_name": "LFA 226: Allakhverdiev vs. Kropschot",
      "fight_id": "bd93ee1e81d25427",
      "gender": "men",
      "is_title": false,
      "method": "TKO (knees to the body)",
      "opponent": "Dedrek Sanders",
      "opponent_elo": 1521.6,
      "outcome": "red_win",
      "post_elo": 1481.8,
      "pre_elo": 1500.0,
      "red_name": "Dedrek Sanders",
      "round": "3",
      "time": "0:20",
      "weight_class": "Lightweight"
    }
  ],
  "first_fight_date": "2026-02-06",
  "gender": "men",
  "history": [
    {
      "date": "2026-02-06",
      "fight_id": "bd93ee1e81d25427",
      "rating": 1481.8,
      "scope": "division",
      "system": "men:Lightweight"
    },
    {
      "date": "2026-02-06",
      "fight_id": "bd93ee1e81d25427",
      "rating": 1483.7,
      "scope": "overall",
      "system": "men:overall"
    }
  ],
  "instagram": null,
  "instagram_featured": false,
  "last_fight_date": "2026-02-06",
  "name": "Nikolay Kiosse",
  "nickname": "",
  "overall_elo": 1483.7,
  "peak_elo": 1500.0,
  "slug": "nikolay-kiosse",
  "systems": {
    "division": "men:Lightweight",
    "overall": "men:overall"
  },
  "weight_class": "Lightweight"
}
