{
  "current_elo": 1500.0,
  "divisional_rank": 222,
  "fight_count": 2,
  "fight_log": [
    {
      "blue_name": "Rabindra Dhant",
      "bout_type": "Flyweight Bout",
      "date": "2023-12-15",
      "elo_delta": -18.0,
      "event_name": "ONE Friday Fights 45: Otop vs. Şen",
      "fight_id": "51ed92b4575e6ad7",
      "gender": "men",
      "is_title": false,
      "method": "Decision (unanimous)",
      "opponent": "Ismail Khan",
      "opponent_elo": 1519.4,
      "outcome": "red_win",
      "post_elo": 1501.4,
      "pre_elo": 1519.4,
      "red_name": "Ismail Khan",
      "round": "3",
      "source": "manual",
      "source_title": "ONE Friday Fights 45",
      "time": "5:00",
      "weight_class": "Flyweight"
    },
    {
      "blue_name": "Torepchi Dongak",
      "bout_type": "Flyweight Bout",
      "date": "2023-09-15",
      "elo_delta": 19.4,
      "event_name": "ONE Friday Fights 33: Yod-IQ vs. Balyko",
      "fight_id": "09a223e8cec09bd5",
      "gender": "men",
      "is_title": false,
      "method": "TKO (punches)",
      "opponent": "Torepchi Dongak",
      "opponent_elo": 1500.0,
      "outcome": "red_win",
      "post_elo": 1519.4,
      "pre_elo": 1500.0,
      "red_name": "Rabindra Dhant",
      "round": "3",
      "source": "manual",
      "source_title": "ONE Friday Fights 33",
      "time": "1:55",
      "weight_class": "Flyweight"
    }
  ],
  "first_fight_date": "2023-09-15",
  "gender": "men",
  "history": [
    {
      "date": "2023-09-15",
      "fight_id": "09a223e8cec09bd5",
      "rating": 1519.4,
      "scope": "division",
      "system": "men:Flyweight"
    },
    {
      "date": "2023-09-15",
      "fight_id": "09a223e8cec09bd5",
      "rating": 1517.3,
      "scope": "overall",
      "system": "men:overall"
    },
    {
      "date": "2023-12-15",
      "fight_id": "51ed92b4575e6ad7",
      "rating": 1501.4,
      "scope": "division",
      "system": "men:Flyweight"
    },
    {
      "date": "2023-12-15",
      "fight_id": "51ed92b4575e6ad7",
      "rating": 1501.3,
      "scope": "overall",
      "system": "men:overall"
    }
  ],
  "inactivity_adjusted": true,
  "instagram": null,
  "instagram_featured": false,
  "last_fight_date": "2023-12-15",
  "name": "Rabindra Dhant",
  "nickname": "",
  "overall_elo": 1500.0,
  "peak_elo": 1519.4,
  "raw_current_elo": 1501.4,
  "raw_overall_elo": 1501.3,
  "slug": "rabindra-dhant",
  "systems": {
    "division": "men:Flyweight",
    "overall": "men:overall"
  },
  "weight_class": "Flyweight"
}
