{
  "current_elo": 1500.0,
  "divisional_rank": 215,
  "fight_count": 27,
  "fight_log": [
    {
      "blue_name": "Tim Means",
      "bout_type": "Welterweight Bout",
      "date": "2019-12-07",
      "elo_delta": -20.3,
      "event_name": "UFC Fight Night: Overeem vs. Rozenstruik",
      "fight_id": "bfa1738e0517e08b",
      "gender": "men",
      "is_title": false,
      "method": "Submission",
      "opponent": "Tim Means",
      "opponent_elo": 1528.4,
      "outcome": "blue_win",
      "post_elo": 1523.6,
      "pre_elo": 1543.9,
      "red_name": "Thiago Alves",
      "round": "1.0",
      "time": "2:38",
      "weight_class": "Welterweight"
    },
    {
      "blue_name": "Laureano Staropoli",
      "bout_type": "Welterweight Bout",
      "date": "2019-05-11",
      "elo_delta": -20.4,
      "event_name": "UFC 237: Namajunas vs. Andrade",
      "fight_id": "7ec9c836803364ff",
      "gender": "men",
      "is_title": false,
      "method": "Decision - Unanimous",
      "opponent": "Laureano Staropoli",
      "opponent_elo": 1517.0,
      "outcome": "blue_win",
      "post_elo": 1543.9,
      "pre_elo": 1564.3,
      "red_name": "Thiago Alves",
      "round": "3.0",
      "time": "5:00",
      "weight_class": "Welterweight"
    },
    {
      "blue_name": "Max Griffin",
      "bout_type": "Welterweight Bout",
      "date": "2019-02-02",
      "elo_delta": 15.0,
      "event_name": "UFC Fight Night: Assuncao vs. Moraes 2",
      "fight_id": "6b7386ac74afd236",
      "gender": "men",
      "is_title": false,
      "method": "Decision - Split",
      "opponent": "Max Griffin",
      "opponent_elo": 1491.8,
      "outcome": "red_win",
      "post_elo": 1564.3,
      "pre_elo": 1549.3,
      "red_name": "Thiago Alves",
      "round": "3.0",
      "time": "5:00",
      "weight_class": "Welterweight"
    },
    {
      "blue_name": "Thiago Alves",
      "bout_type": "Welterweight Bout",
      "date": "2018-09-15",
      "elo_delta": -21.6,
      "event_name": "UFC Fight Night: Hunt vs. Oleinik",
      "fight_id": "9349591fc63ddcdb",
      "gender": "men",
      "is_title": false,
      "method": "Decision - Unanimous",
      "opponent": "Aleksei Kunchenko",
      "opponent_elo": 1500.0,
      "outcome": "red_win",
      "post_elo": 1549.3,
      "pre_elo": 1570.9,
      "red_name": "Aleksei Kunchenko",
      "round": "3.0",
      "time": "5:00",
      "weight_class": "Welterweight"
    },
    {
      "blue_name": "Curtis Millender",
      "bout_type": "Welterweight Bout",
      "date": "2018-02-18",
      "elo_delta": -24.7,
      "event_name": "UFC Fight Night: Cerrone vs. Medeiros",
      "fight_id": "a9cc00d4b6b43a47",
      "gender": "men",
      "is_title": false,
      "method": "KO/TKO",
      "opponent": "Curtis Millender",
      "opponent_elo": 1500.0,
      "outcome": "blue_win",
      "post_elo": 1570.9,
      "pre_elo": 1595.5,
      "red_name": "Thiago Alves",
      "round": "2.0",
      "time": "4:17",
      "weight_class": "Welterweight"
    },
    {
      "blue_name": "Patrick Cote",
      "bout_type": "Welterweight Bout",
      "date": "2017-04-08",
      "elo_delta": 16.7,
      "event_name": "UFC 210: Cormier vs. Johnson 2",
      "fight_id": "9c24b4ec956ff561",
      "gender": "men",
      "is_title": false,
      "method": "Decision - Unanimous",
      "opponent": "Patrick Cote",
      "opponent_elo": 1554.3,
      "outcome": "red_win",
      "post_elo": 1595.5,
      "pre_elo": 1578.8,
      "red_name": "Thiago Alves",
      "round": "3.0",
      "time": "5:00",
      "weight_class": "Welterweight"
    },
    {
      "blue_name": "Thiago Alves",
      "bout_type": "Catch Weight Bout",
      "date": "2016-11-12",
      "elo_delta": -25.5,
      "event_name": "UFC 205: Alvarez vs McGregor",
      "fight_id": "c9eda32f97ae53d3",
      "gender": "men",
      "is_title": false,
      "method": "Decision - Unanimous",
      "opponent": "Jim Miller",
      "opponent_elo": 1623.2,
      "outcome": "red_win",
      "post_elo": 1578.8,
      "pre_elo": 1604.3,
      "red_name": "Jim Miller",
      "round": "3.0",
      "time": "5:00",
      "weight_class": "Catch Weight"
    },
    {
      "blue_name": "Thiago Alves",
      "bout_type": "Welterweight Bout",
      "date": "2015-05-30",
      "elo_delta": -19.2,
      "event_name": "UFC Fight Night: Condit vs Alves",
      "fight_id": "8aaf89b341be66f8",
      "gender": "men",
      "is_title": false,
      "method": "TKO - Doctor's Stoppage",
      "opponent": "Carlos Condit",
      "opponent_elo": 1627.5,
      "outcome": "red_win",
      "post_elo": 1604.3,
      "pre_elo": 1623.6,
      "red_name": "Carlos Condit",
      "round": "2.0",
      "time": "5:00",
      "weight_class": "Welterweight"
    },
    {
      "blue_name": "Thiago Alves",
      "bout_type": "Welterweight Bout",
      "date": "2015-01-31",
      "elo_delta": 17.1,
      "event_name": "UFC 183: Silva vs Diaz",
      "fight_id": "3ce0b2744dc0a063",
      "gender": "men",
      "is_title": false,
      "method": "KO/TKO",
      "opponent": "Jordan Mein",
      "opponent_elo": 1564.1,
      "outcome": "blue_win",
      "post_elo": 1623.6,
      "pre_elo": 1606.5,
      "red_name": "Jordan Mein",
      "round": "2.0",
      "time": "0:39",
      "weight_class": "Welterweight"
    },
    {
      "blue_name": "Seth Baczynski",
      "bout_type": "Welterweight Bout",
      "date": "2014-04-19",
      "elo_delta": 15.3,
      "event_name": "UFC on FOX: Werdum vs Browne",
      "fight_id": "78ba9693f0d10a48",
      "gender": "men",
      "is_title": false,
      "method": "Decision - Unanimous",
      "opponent": "Seth Baczynski",
      "opponent_elo": 1538.8,
      "outcome": "red_win",
      "post_elo": 1606.5,
      "pre_elo": 1591.2,
      "red_name": "Thiago Alves",
      "round": "3.0",
      "time": "5:00",
      "weight_class": "Welterweight"
    },
    {
      "blue_name": "Martin Kampmann",
      "bout_type": "Welterweight Bout",
      "date": "2012-03-02",
      "elo_delta": -20.5,
      "event_name": "UFC on FX: Alves vs Kampmann",
      "fight_id": "1c7c7183cd675ed3",
      "gender": "men",
      "is_title": false,
      "method": "Submission",
      "opponent": "Martin Kampmann",
      "opponent_elo": 1592.1,
      "outcome": "blue_win",
      "post_elo": 1591.2,
      "pre_elo": 1611.7,
      "red_name": "Thiago Alves",
      "round": "3.0",
      "time": "4:12",
      "weight_class": "Welterweight"
    },
    {
      "blue_name": "Papy Abedi",
      "bout_type": "Welterweight Bout",
      "date": "2011-11-05",
      "elo_delta": 14.1,
      "event_name": "UFC 138: Leben vs Munoz",
      "fight_id": "12e8b877c8b73f1c",
      "gender": "men",
      "is_title": false,
      "method": "Submission",
      "opponent": "Papy Abedi",
      "opponent_elo": 1500.0,
      "outcome": "red_win",
      "post_elo": 1611.7,
      "pre_elo": 1597.6,
      "red_name": "Thiago Alves",
      "round": "1.0",
      "time": "3:32",
      "weight_class": "Welterweight"
    },
    {
      "blue_name": "Rick Story",
      "bout_type": "Welterweight Bout",
      "date": "2011-05-28",
      "elo_delta": -19.9,
      "event_name": "UFC 130: Rampage vs Hamill",
      "fight_id": "84af4aa322df217b",
      "gender": "men",
      "is_title": false,
      "method": "Decision - Unanimous",
      "opponent": "Rick Story",
      "opponent_elo": 1580.8,
      "outcome": "blue_win",
      "post_elo": 1597.6,
      "pre_elo": 1617.5,
      "red_name": "Thiago Alves",
      "round": "3.0",
      "time": "5:00",
      "weight_class": "Welterweight"
    },
    {
      "blue_name": "John Howard",
      "bout_type": "Welterweight Bout",
      "date": "2010-12-11",
      "elo_delta": 15.2,
      "event_name": "UFC 124: St-Pierre vs Koscheck 2",
      "fight_id": "6299806d578c181a",
      "gender": "men",
      "is_title": false,
      "method": "Decision - Unanimous",
      "opponent": "John Howard",
      "opponent_elo": 1547.8,
      "outcome": "red_win",
      "post_elo": 1617.5,
      "pre_elo": 1602.3,
      "red_name": "Thiago Alves",
      "round": "3.0",
      "time": "5:00",
      "weight_class": "Welterweight"
    },
    {
      "blue_name": "Thiago Alves",
      "bout_type": "Welterweight Bout",
      "date": "2010-08-07",
      "elo_delta": -15.3,
      "event_name": "UFC 117: Silva vs Sonnen",
      "fight_id": "6b29f63acd972277",
      "gender": "men",
      "is_title": false,
      "method": "Decision - Unanimous",
      "opponent": "Jon Fitch",
      "opponent_elo": 1669.7,
      "outcome": "red_win",
      "post_elo": 1602.3,
      "pre_elo": 1617.6,
      "red_name": "Jon Fitch",
      "round": "3.0",
      "time": "5:00",
      "weight_class": "Welterweight"
    },
    {
      "blue_name": "Thiago Alves",
      "bout_type": "UFC Welterweight Title Bout",
      "date": "2009-07-11",
      "elo_delta": -17.0,
      "event_name": "UFC 100",
      "fight_id": "a51dc9f612d9b837",
      "gender": "men",
      "is_title": true,
      "method": "Decision - Unanimous",
      "opponent": "Georges St-Pierre",
      "opponent_elo": 1683.8,
      "outcome": "red_win",
      "post_elo": 1617.6,
      "pre_elo": 1634.6,
      "red_name": "Georges St-Pierre",
      "round": "5.0",
      "time": "5:00",
      "weight_class": "Welterweight"
    },
    {
      "blue_name": "Josh Koscheck",
      "bout_type": "Welterweight Bout",
      "date": "2008-10-25",
      "elo_delta": 17.7,
      "event_name": "UFC 90: Silva vs Cote",
      "fight_id": "6d3909ce0752d2c4",
      "gender": "men",
      "is_title": false,
      "method": "Decision - Unanimous",
      "opponent": "Josh Koscheck",
      "opponent_elo": 1610.8,
      "outcome": "red_win",
      "post_elo": 1634.6,
      "pre_elo": 1616.9,
      "red_name": "Thiago Alves",
      "round": "3.0",
      "time": "5:00",
      "weight_class": "Welterweight"
    },
    {
      "blue_name": "Matt Hughes",
      "bout_type": "Welterweight Bout",
      "date": "2008-06-07",
      "elo_delta": 22.6,
      "event_name": "UFC 85: Bedlam",
      "fight_id": "0ae5e7ad88c3022b",
      "gender": "men",
      "is_title": false,
      "method": "KO/TKO",
      "opponent": "Matt Hughes",
      "opponent_elo": 1651.3,
      "outcome": "red_win",
      "post_elo": 1616.9,
      "pre_elo": 1594.4,
      "red_name": "Thiago Alves",
      "round": "2.0",
      "time": "1:02",
      "weight_class": "Welterweight"
    },
    {
      "blue_name": "Karo Parisyan",
      "bout_type": "Welterweight Bout",
      "date": "2008-04-02",
      "elo_delta": 21.1,
      "event_name": "UFC Fight Night: Florian vs Lauzon",
      "fight_id": "03eb95e830f259b6",
      "gender": "men",
      "is_title": false,
      "method": "KO/TKO",
      "opponent": "Karo Parisyan",
      "opponent_elo": 1602.4,
      "outcome": "red_win",
      "post_elo": 1594.4,
      "pre_elo": 1573.3,
      "red_name": "Thiago Alves",
      "round": "2.0",
      "time": "0:24",
      "weight_class": "Welterweight"
    },
    {
      "blue_name": "Chris Lytle",
      "bout_type": "Welterweight Bout",
      "date": "2007-11-17",
      "elo_delta": 14.3,
      "event_name": "UFC 78: Validation",
      "fight_id": "495f829971cf885b",
      "gender": "men",
      "is_title": false,
      "method": "TKO - Doctor's Stoppage",
      "opponent": "Chris Lytle",
      "opponent_elo": 1464.5,
      "outcome": "red_win",
      "post_elo": 1573.3,
      "pre_elo": 1559.0,
      "red_name": "Thiago Alves",
      "round": "2.0",
      "time": "5:00",
      "weight_class": "Welterweight"
    },
    {
      "blue_name": "Kuniyoshi Hironaka",
      "bout_type": "Welterweight Bout",
      "date": "2007-09-19",
      "elo_delta": 19.4,
      "event_name": "UFC Fight Night: Thomas vs Florian",
      "fight_id": "7ec3b71af9bd2471",
      "gender": "men",
      "is_title": false,
      "method": "KO/TKO",
      "opponent": "Kuniyoshi Hironaka",
      "opponent_elo": 1539.3,
      "outcome": "red_win",
      "post_elo": 1559.0,
      "pre_elo": 1539.6,
      "red_name": "Thiago Alves",
      "round": "2.0",
      "time": "4:04",
      "weight_class": "Welterweight"
    },
    {
      "blue_name": "Tony Desouza",
      "bout_type": "Welterweight Bout",
      "date": "2006-12-30",
      "elo_delta": 20.1,
      "event_name": "UFC 66: Liddell vs Ortiz 2",
      "fight_id": "8535f0e0607df1ef",
      "gender": "men",
      "is_title": false,
      "method": "KO/TKO",
      "opponent": "Tony Desouza",
      "opponent_elo": 1532.1,
      "outcome": "red_win",
      "post_elo": 1539.6,
      "pre_elo": 1519.4,
      "red_name": "Thiago Alves",
      "round": "2.0",
      "time": "1:10",
      "weight_class": "Welterweight"
    },
    {
      "blue_name": "John Alessio",
      "bout_type": "Welterweight Bout",
      "date": "2006-10-10",
      "elo_delta": 17.5,
      "event_name": "Ortiz vs Shamrock 3: The Final Chapter",
      "fight_id": "7e219b4309aff1fc",
      "gender": "men",
      "is_title": false,
      "method": "Decision - Unanimous",
      "opponent": "John Alessio",
      "opponent_elo": 1492.4,
      "outcome": "red_win",
      "post_elo": 1519.4,
      "pre_elo": 1501.9,
      "red_name": "Thiago Alves",
      "round": "3.0",
      "time": "5:00",
      "weight_class": "Welterweight"
    },
    {
      "blue_name": "Thiago Alves",
      "bout_type": "Welterweight Bout",
      "date": "2006-06-28",
      "elo_delta": -18.5,
      "event_name": "UFC Fight Night 5",
      "fight_id": "09192976dcc0addb",
      "gender": "men",
      "is_title": false,
      "method": "KO/TKO",
      "opponent": "Jon Fitch",
      "opponent_elo": 1536.7,
      "outcome": "red_win",
      "post_elo": 1501.9,
      "pre_elo": 1520.5,
      "red_name": "Jon Fitch",
      "round": "2.0",
      "time": "4:37",
      "weight_class": "Welterweight"
    },
    {
      "blue_name": "Derrick Noble",
      "bout_type": "Welterweight Bout",
      "date": "2006-04-15",
      "elo_delta": 19.4,
      "event_name": "UFC 59: Reality Check",
      "fight_id": "6f0b6158192e9d85",
      "gender": "men",
      "is_title": false,
      "method": "KO/TKO",
      "opponent": "Derrick Noble",
      "opponent_elo": 1500.0,
      "outcome": "red_win",
      "post_elo": 1520.5,
      "pre_elo": 1501.1,
      "red_name": "Thiago Alves",
      "round": "1.0",
      "time": "2:54",
      "weight_class": "Welterweight"
    },
    {
      "blue_name": "Ansar Chalangov",
      "bout_type": "Welterweight Bout",
      "date": "2005-11-19",
      "elo_delta": 20.5,
      "event_name": "UFC 56: Full Force",
      "fight_id": "4e13a5d54d715cef",
      "gender": "men",
      "is_title": false,
      "method": "KO/TKO",
      "opponent": "Ansar Chalangov",
      "opponent_elo": 1500.0,
      "outcome": "red_win",
      "post_elo": 1501.1,
      "pre_elo": 1480.6,
      "red_name": "Thiago Alves",
      "round": "1.0",
      "time": "2:25",
      "weight_class": "Welterweight"
    },
    {
      "blue_name": "Thiago Alves",
      "bout_type": "Welterweight Bout",
      "date": "2005-10-03",
      "elo_delta": -19.4,
      "event_name": "UFC Fight Night 2",
      "fight_id": "0b31a9e7ea7acb4d",
      "gender": "men",
      "is_title": false,
      "method": "Submission",
      "opponent": "Spencer Fisher",
      "opponent_elo": 1500.0,
      "outcome": "red_win",
      "post_elo": 1480.6,
      "pre_elo": 1500.0,
      "red_name": "Spencer Fisher",
      "round": "2.0",
      "time": "4:43",
      "weight_class": "Welterweight"
    }
  ],
  "first_fight_date": "2005-10-03",
  "gender": "men",
  "history": [
    {
      "date": "2005-10-03",
      "fight_id": "0b31a9e7ea7acb4d",
      "rating": 1480.6,
      "scope": "division",
      "system": "men:Welterweight"
    },
    {
      "date": "2005-10-03",
      "fight_id": "0b31a9e7ea7acb4d",
      "rating": 1482.7,
      "scope": "overall",
      "system": "men:overall"
    },
    {
      "date": "2005-11-19",
      "fight_id": "4e13a5d54d715cef",
      "rating": 1501.1,
      "scope": "division",
      "system": "men:Welterweight"
    },
    {
      "date": "2005-11-19",
      "fight_id": "4e13a5d54d715cef",
      "rating": 1500.9,
      "scope": "overall",
      "system": "men:overall"
    },
    {
      "date": "2006-04-15",
      "fight_id": "6f0b6158192e9d85",
      "rating": 1520.5,
      "scope": "division",
      "system": "men:Welterweight"
    },
    {
      "date": "2006-04-15",
      "fight_id": "6f0b6158192e9d85",
      "rating": 1518.1,
      "scope": "overall",
      "system": "men:overall"
    },
    {
      "date": "2006-06-28",
      "fight_id": "09192976dcc0addb",
      "rating": 1501.9,
      "scope": "division",
      "system": "men:Welterweight"
    },
    {
      "date": "2006-06-28",
      "fight_id": "09192976dcc0addb",
      "rating": 1501.6,
      "scope": "overall",
      "system": "men:overall"
    },
    {
      "date": "2006-10-10",
      "fight_id": "7e219b4309aff1fc",
      "rating": 1519.4,
      "scope": "division",
      "system": "men:Welterweight"
    },
    {
      "date": "2006-10-10",
      "fight_id": "7e219b4309aff1fc",
      "rating": 1518.0,
      "scope": "overall",
      "system": "men:overall"
    },
    {
      "date": "2006-12-30",
      "fight_id": "8535f0e0607df1ef",
      "rating": 1539.6,
      "scope": "division",
      "system": "men:Welterweight"
    },
    {
      "date": "2006-12-30",
      "fight_id": "8535f0e0607df1ef",
      "rating": 1535.8,
      "scope": "overall",
      "system": "men:overall"
    },
    {
      "date": "2007-09-19",
      "fight_id": "7ec3b71af9bd2471",
      "rating": 1559.0,
      "scope": "division",
      "system": "men:Welterweight"
    },
    {
      "date": "2007-09-19",
      "fight_id": "7ec3b71af9bd2471",
      "rating": 1553.2,
      "scope": "overall",
      "system": "men:overall"
    },
    {
      "date": "2007-11-17",
      "fight_id": "495f829971cf885b",
      "rating": 1573.3,
      "scope": "division",
      "system": "men:Welterweight"
    },
    {
      "date": "2007-11-17",
      "fight_id": "495f829971cf885b",
      "rating": 1568.4,
      "scope": "overall",
      "system": "men:overall"
    },
    {
      "date": "2008-04-02",
      "fight_id": "03eb95e830f259b6",
      "rating": 1594.4,
      "scope": "division",
      "system": "men:Welterweight"
    },
    {
      "date": "2008-04-02",
      "fight_id": "03eb95e830f259b6",
      "rating": 1586.9,
      "scope": "overall",
      "system": "men:overall"
    },
    {
      "date": "2008-06-07",
      "fight_id": "0ae5e7ad88c3022b",
      "rating": 1616.9,
      "scope": "division",
      "system": "men:Welterweight"
    },
    {
      "date": "2008-06-07",
      "fight_id": "0ae5e7ad88c3022b",
      "rating": 1607.0,
      "scope": "overall",
      "system": "men:overall"
    },
    {
      "date": "2008-10-25",
      "fight_id": "6d3909ce0752d2c4",
      "rating": 1634.6,
      "scope": "division",
      "system": "men:Welterweight"
    },
    {
      "date": "2008-10-25",
      "fight_id": "6d3909ce0752d2c4",
      "rating": 1622.8,
      "scope": "overall",
      "system": "men:overall"
    },
    {
      "date": "2009-07-11",
      "fight_id": "a51dc9f612d9b837",
      "rating": 1617.6,
      "scope": "division",
      "system": "men:Welterweight"
    },
    {
      "date": "2009-07-11",
      "fight_id": "a51dc9f612d9b837",
      "rating": 1607.6,
      "scope": "overall",
      "system": "men:overall"
    },
    {
      "date": "2010-08-07",
      "fight_id": "6b29f63acd972277",
      "rating": 1602.3,
      "scope": "division",
      "system": "men:Welterweight"
    },
    {
      "date": "2010-08-07",
      "fight_id": "6b29f63acd972277",
      "rating": 1593.8,
      "scope": "overall",
      "system": "men:overall"
    },
    {
      "date": "2010-12-11",
      "fight_id": "6299806d578c181a",
      "rating": 1617.5,
      "scope": "division",
      "system": "men:Welterweight"
    },
    {
      "date": "2010-12-11",
      "fight_id": "6299806d578c181a",
      "rating": 1607.5,
      "scope": "overall",
      "system": "men:overall"
    },
    {
      "date": "2011-05-28",
      "fight_id": "84af4aa322df217b",
      "rating": 1597.6,
      "scope": "division",
      "system": "men:Welterweight"
    },
    {
      "date": "2011-05-28",
      "fight_id": "84af4aa322df217b",
      "rating": 1589.8,
      "scope": "overall",
      "system": "men:overall"
    },
    {
      "date": "2011-11-05",
      "fight_id": "12e8b877c8b73f1c",
      "rating": 1611.7,
      "scope": "division",
      "system": "men:Welterweight"
    },
    {
      "date": "2011-11-05",
      "fight_id": "12e8b877c8b73f1c",
      "rating": 1602.8,
      "scope": "overall",
      "system": "men:overall"
    },
    {
      "date": "2012-03-02",
      "fight_id": "1c7c7183cd675ed3",
      "rating": 1591.2,
      "scope": "division",
      "system": "men:Welterweight"
    },
    {
      "date": "2012-03-02",
      "fight_id": "1c7c7183cd675ed3",
      "rating": 1584.9,
      "scope": "overall",
      "system": "men:overall"
    },
    {
      "date": "2014-04-19",
      "fight_id": "78ba9693f0d10a48",
      "rating": 1606.5,
      "scope": "division",
      "system": "men:Welterweight"
    },
    {
      "date": "2014-04-19",
      "fight_id": "78ba9693f0d10a48",
      "rating": 1598.6,
      "scope": "overall",
      "system": "men:overall"
    },
    {
      "date": "2015-01-31",
      "fight_id": "3ce0b2744dc0a063",
      "rating": 1623.6,
      "scope": "division",
      "system": "men:Welterweight"
    },
    {
      "date": "2015-01-31",
      "fight_id": "3ce0b2744dc0a063",
      "rating": 1613.8,
      "scope": "overall",
      "system": "men:overall"
    },
    {
      "date": "2015-05-30",
      "fight_id": "8aaf89b341be66f8",
      "rating": 1604.3,
      "scope": "division",
      "system": "men:Welterweight"
    },
    {
      "date": "2015-05-30",
      "fight_id": "8aaf89b341be66f8",
      "rating": 1596.6,
      "scope": "overall",
      "system": "men:overall"
    },
    {
      "date": "2016-11-12",
      "fight_id": "c9eda32f97ae53d3",
      "rating": 1578.8,
      "scope": "division",
      "system": "men:Welterweight"
    },
    {
      "date": "2016-11-12",
      "fight_id": "c9eda32f97ae53d3",
      "rating": 1574.0,
      "scope": "overall",
      "system": "men:overall"
    },
    {
      "date": "2017-04-08",
      "fight_id": "9c24b4ec956ff561",
      "rating": 1595.5,
      "scope": "division",
      "system": "men:Welterweight"
    },
    {
      "date": "2017-04-08",
      "fight_id": "9c24b4ec956ff561",
      "rating": 1588.7,
      "scope": "overall",
      "system": "men:overall"
    },
    {
      "date": "2018-02-18",
      "fight_id": "a9cc00d4b6b43a47",
      "rating": 1570.9,
      "scope": "division",
      "system": "men:Welterweight"
    },
    {
      "date": "2018-02-18",
      "fight_id": "a9cc00d4b6b43a47",
      "rating": 1567.1,
      "scope": "overall",
      "system": "men:overall"
    },
    {
      "date": "2018-09-15",
      "fight_id": "9349591fc63ddcdb",
      "rating": 1549.3,
      "scope": "division",
      "system": "men:Welterweight"
    },
    {
      "date": "2018-09-15",
      "fight_id": "9349591fc63ddcdb",
      "rating": 1548.1,
      "scope": "overall",
      "system": "men:overall"
    },
    {
      "date": "2019-02-02",
      "fight_id": "6b7386ac74afd236",
      "rating": 1564.3,
      "scope": "division",
      "system": "men:Welterweight"
    },
    {
      "date": "2019-02-02",
      "fight_id": "6b7386ac74afd236",
      "rating": 1561.5,
      "scope": "overall",
      "system": "men:overall"
    },
    {
      "date": "2019-05-11",
      "fight_id": "7ec9c836803364ff",
      "rating": 1543.9,
      "scope": "division",
      "system": "men:Welterweight"
    },
    {
      "date": "2019-05-11",
      "fight_id": "7ec9c836803364ff",
      "rating": 1543.4,
      "scope": "overall",
      "system": "men:overall"
    },
    {
      "date": "2019-12-07",
      "fight_id": "bfa1738e0517e08b",
      "rating": 1523.6,
      "scope": "division",
      "system": "men:Welterweight"
    },
    {
      "date": "2019-12-07",
      "fight_id": "bfa1738e0517e08b",
      "rating": 1525.4,
      "scope": "overall",
      "system": "men:overall"
    }
  ],
  "instagram": null,
  "instagram_featured": false,
  "last_fight_date": "2019-12-07",
  "name": "Thiago Alves",
  "nickname": "",
  "overall_elo": 1500.0,
  "peak_elo": 1634.6,
  "slug": "thiago-alves",
  "systems": {
    "division": "men:Welterweight",
    "overall": "men:overall"
  },
  "weight_class": "Welterweight"
}
