{
  "current_elo": 1500.0,
  "divisional_rank": 372,
  "fight_count": 7,
  "fight_log": [
    {
      "blue_name": "Takehiro Ishii",
      "bout_type": "Open Weight Bout",
      "date": "2004-03-04",
      "elo_delta": 1.4,
      "event_name": "Shooto: 3/4 in Kitazawa Town Hall",
      "fight_id": "cd4c9a1c380135be",
      "gender": "men",
      "is_title": false,
      "method": "Draw",
      "opponent": "Takehiro Ishii",
      "opponent_elo": 1517.3,
      "outcome": "draw",
      "post_elo": 1491.2,
      "pre_elo": 1489.8,
      "red_name": "Toshiteru Ishii",
      "round": "2",
      "source": "manual",
      "source_title": "2004 in Shooto",
      "time": "5:00",
      "weight_class": "Open Weight"
    },
    {
      "blue_name": "Toshiteru Ishii",
      "bout_type": "Open Weight Bout",
      "date": "2003-02-06",
      "elo_delta": -20.0,
      "event_name": "Shooto: 2/6 in Kitazawa Town Hall",
      "fight_id": "c0053040fe6fa638",
      "gender": "men",
      "is_title": false,
      "method": "Decision (Unanimous)",
      "opponent": "Daiji Takahashi",
      "opponent_elo": 1470.5,
      "outcome": "red_win",
      "post_elo": 1489.8,
      "pre_elo": 1509.8,
      "red_name": "Daiji Takahashi",
      "round": "2",
      "source": "manual",
      "source_title": "2003 in Shooto",
      "time": "5:00",
      "weight_class": "Open Weight"
    },
    {
      "blue_name": "Takahisa Toyoshima",
      "bout_type": "Open Weight Bout",
      "date": "2002-07-27",
      "elo_delta": 17.4,
      "event_name": "Shooto: Treasure Hunt 9",
      "fight_id": "dec4f098f3272ed9",
      "gender": "men",
      "is_title": false,
      "method": "Decision (Majority)",
      "opponent": "Takahisa Toyoshima",
      "opponent_elo": 1480.6,
      "outcome": "red_win",
      "post_elo": 1509.8,
      "pre_elo": 1492.4,
      "red_name": "Toshiteru Ishii",
      "round": "2",
      "source": "manual",
      "source_title": "2002 in Shooto",
      "time": "5:00",
      "weight_class": "Open Weight"
    },
    {
      "blue_name": "Toshiteru Ishii",
      "bout_type": "Open Weight Bout",
      "date": "2002-01-25",
      "elo_delta": -22.4,
      "event_name": "Shooto: Treasure Hunt 2",
      "fight_id": "c25a5cf91e43fb9c",
      "gender": "men",
      "is_title": false,
      "method": "Technical Submission (Kimura)",
      "opponent": "Junji Ikoma",
      "opponent_elo": 1462.2,
      "outcome": "red_win",
      "post_elo": 1492.4,
      "pre_elo": 1514.8,
      "red_name": "Junji Ikoma",
      "round": "1",
      "source": "manual",
      "source_title": "2002 in Shooto",
      "time": "2:35",
      "weight_class": "Open Weight"
    },
    {
      "blue_name": "Toshiteru Ishii",
      "bout_type": "Open Weight Bout",
      "date": "2001-09-27",
      "elo_delta": -20.7,
      "event_name": "Shooto: To The Top 9",
      "fight_id": "eabe1775b4d80904",
      "gender": "men",
      "is_title": false,
      "method": "Decision (Unanimous)",
      "opponent": "Homare Kuboyama",
      "opponent_elo": 1483.9,
      "outcome": "red_win",
      "post_elo": 1514.8,
      "pre_elo": 1535.4,
      "red_name": "Homare Kuboyama",
      "round": "2",
      "source": "manual",
      "source_title": "2001 in Shooto",
      "time": "5:00",
      "weight_class": "Open Weight"
    },
    {
      "blue_name": "Katsuhisa Akasaki",
      "bout_type": "Open Weight Bout",
      "date": "2001-03-21",
      "elo_delta": 17.4,
      "event_name": "Shooto: To The Top 3",
      "fight_id": "193799b4bfdcf60e",
      "gender": "men",
      "is_title": false,
      "method": "DQ (Kneeing to the Head on the Ground)",
      "opponent": "Katsuhisa Akasaki",
      "opponent_elo": 1482.0,
      "outcome": "red_win",
      "post_elo": 1535.4,
      "pre_elo": 1518.0,
      "red_name": "Toshiteru Ishii",
      "round": "2",
      "source": "manual",
      "source_title": "2001 in Shooto",
      "time": "2:46",
      "weight_class": "Open Weight"
    },
    {
      "blue_name": "Tomohiro Hashi",
      "bout_type": "Open Weight Bout",
      "date": "2001-01-19",
      "elo_delta": 18.0,
      "event_name": "Shooto: To The Top 1",
      "fight_id": "bf16ab7a91921867",
      "gender": "men",
      "is_title": false,
      "method": "Decision (Unanimous)",
      "opponent": "Tomohiro Hashi",
      "opponent_elo": 1500.0,
      "outcome": "red_win",
      "post_elo": 1518.0,
      "pre_elo": 1500.0,
      "red_name": "Toshiteru Ishii",
      "round": "2",
      "source": "manual",
      "source_title": "2001 in Shooto",
      "time": "5:00",
      "weight_class": "Open Weight"
    }
  ],
  "first_fight_date": "2001-01-19",
  "gender": "men",
  "history": [
    {
      "date": "2001-01-19",
      "fight_id": "bf16ab7a91921867",
      "rating": 1518.0,
      "scope": "division",
      "system": "men:Open Weight"
    },
    {
      "date": "2001-01-19",
      "fight_id": "bf16ab7a91921867",
      "rating": 1516.0,
      "scope": "overall",
      "system": "men:overall"
    },
    {
      "date": "2001-03-21",
      "fight_id": "193799b4bfdcf60e",
      "rating": 1535.4,
      "scope": "division",
      "system": "men:Open Weight"
    },
    {
      "date": "2001-03-21",
      "fight_id": "193799b4bfdcf60e",
      "rating": 1531.7,
      "scope": "overall",
      "system": "men:overall"
    },
    {
      "date": "2001-09-27",
      "fight_id": "eabe1775b4d80904",
      "rating": 1514.8,
      "scope": "division",
      "system": "men:Open Weight"
    },
    {
      "date": "2001-09-27",
      "fight_id": "eabe1775b4d80904",
      "rating": 1513.6,
      "scope": "overall",
      "system": "men:overall"
    },
    {
      "date": "2002-01-25",
      "fight_id": "c25a5cf91e43fb9c",
      "rating": 1492.4,
      "scope": "division",
      "system": "men:Open Weight"
    },
    {
      "date": "2002-01-25",
      "fight_id": "c25a5cf91e43fb9c",
      "rating": 1494.0,
      "scope": "overall",
      "system": "men:overall"
    },
    {
      "date": "2002-07-27",
      "fight_id": "dec4f098f3272ed9",
      "rating": 1509.8,
      "scope": "division",
      "system": "men:Open Weight"
    },
    {
      "date": "2002-07-27",
      "fight_id": "dec4f098f3272ed9",
      "rating": 1509.5,
      "scope": "overall",
      "system": "men:overall"
    },
    {
      "date": "2003-02-06",
      "fight_id": "c0053040fe6fa638",
      "rating": 1489.8,
      "scope": "division",
      "system": "men:Open Weight"
    },
    {
      "date": "2003-02-06",
      "fight_id": "c0053040fe6fa638",
      "rating": 1491.8,
      "scope": "overall",
      "system": "men:overall"
    },
    {
      "date": "2004-03-04",
      "fight_id": "cd4c9a1c380135be",
      "rating": 1491.2,
      "scope": "division",
      "system": "men:Open Weight"
    },
    {
      "date": "2004-03-04",
      "fight_id": "cd4c9a1c380135be",
      "rating": 1492.9,
      "scope": "overall",
      "system": "men:overall"
    }
  ],
  "inactivity_adjusted": true,
  "instagram": null,
  "instagram_featured": false,
  "last_fight_date": "2004-03-04",
  "name": "Toshiteru Ishii",
  "nickname": "",
  "overall_elo": 1500.0,
  "peak_elo": 1535.4,
  "raw_current_elo": 1491.2,
  "raw_overall_elo": 1492.9,
  "slug": "toshiteru-ishii",
  "systems": {
    "division": "men:Open Weight",
    "overall": "men:overall"
  },
  "weight_class": "Open Weight"
}
