{
  "activity_status": "inactive",
  "current_elo": 1500.0,
  "days_since_last_fight": 1456,
  "divisional_rank": 579,
  "fight_count": 3,
  "fight_log": [
    {
      "blue_name": "Emmanuel Sanchez",
      "bout_type": "Lightweight Bout",
      "date": "2022-04-23",
      "elo_delta": 17.4,
      "event_name": "Bellator 279: Cyborg vs. Blencowe 2",
      "fight_id": "812bb8dc0e7e6392",
      "gender": "men",
      "is_title": false,
      "method": "Decision (unanimous) (29–28, 30–27, 30–27)",
      "opponent": "Emmanuel Sanchez",
      "opponent_elo": 1453.0,
      "outcome": "red_win",
      "post_elo": 1481.4,
      "pre_elo": 1463.9,
      "red_name": "Yancy Medeiros",
      "round": "3",
      "source": "manual",
      "source_title": "Bellator 279",
      "time": "5:00",
      "weight_class": "Lightweight"
    },
    {
      "blue_name": "Damir Hadzovic",
      "bout_type": "Lightweight Bout",
      "date": "2021-06-26",
      "elo_delta": -18.1,
      "event_name": "UFC Fight Night: Gane vs. Volkov",
      "fight_id": "3640b6a517f4e745",
      "gender": "men",
      "is_title": false,
      "method": "Decision - Unanimous",
      "opponent": "Damir Hadzovic",
      "opponent_elo": 1480.6,
      "outcome": "blue_win",
      "post_elo": 1463.9,
      "pre_elo": 1482.0,
      "red_name": "Yancy Medeiros",
      "round": "3.0",
      "source": "https://raw.githubusercontent.com/komaksym/UFC-DataLab/main/data/stats/stats_processed_all_bouts.csv",
      "source_title": "",
      "time": "5:00",
      "weight_class": "Lightweight"
    },
    {
      "blue_name": "Yancy Medeiros",
      "bout_type": "Lightweight Bout",
      "date": "2020-02-15",
      "elo_delta": -18.0,
      "event_name": "UFC Fight Night: Anderson vs. Blachowicz",
      "fight_id": "a8152650c3711ea0",
      "gender": "men",
      "is_title": false,
      "method": "Decision - Unanimous",
      "opponent": "Lando Vannata",
      "opponent_elo": 1500.0,
      "outcome": "red_win",
      "post_elo": 1482.0,
      "pre_elo": 1500.0,
      "red_name": "Lando Vannata",
      "round": "3.0",
      "source": "https://raw.githubusercontent.com/komaksym/UFC-DataLab/main/data/stats/stats_processed_all_bouts.csv",
      "source_title": "",
      "time": "5:00",
      "weight_class": "Lightweight"
    }
  ],
  "first_fight_date": "2020-02-15",
  "gender": "men",
  "history": [
    {
      "date": "2020-02-15",
      "fight_id": "a8152650c3711ea0",
      "rating": 1482.0,
      "scope": "division",
      "system": "men:Lightweight"
    },
    {
      "date": "2020-02-15",
      "fight_id": "a8152650c3711ea0",
      "rating": 1484.0,
      "scope": "overall",
      "system": "men:overall"
    },
    {
      "date": "2021-06-26",
      "fight_id": "3640b6a517f4e745",
      "rating": 1463.9,
      "scope": "division",
      "system": "men:Lightweight"
    },
    {
      "date": "2021-06-26",
      "fight_id": "3640b6a517f4e745",
      "rating": 1467.9,
      "scope": "overall",
      "system": "men:overall"
    },
    {
      "date": "2022-04-23",
      "fight_id": "812bb8dc0e7e6392",
      "rating": 1481.4,
      "scope": "division",
      "system": "men:Lightweight"
    },
    {
      "date": "2022-04-23",
      "fight_id": "812bb8dc0e7e6392",
      "rating": 1483.3,
      "scope": "overall",
      "system": "men:overall"
    }
  ],
  "inactive_after_days": 545,
  "inactivity_adjusted": true,
  "instagram": null,
  "instagram_featured": false,
  "last_fight_date": "2022-04-23",
  "name": "Yancy Medeiros",
  "nickname": "",
  "overall_elo": 1500.0,
  "peak_elo": 1500.0,
  "raw_current_elo": 1481.4,
  "raw_overall_elo": 1483.3,
  "slug": "yancy-medeiros",
  "systems": {
    "division": "men:Lightweight",
    "overall": "men:overall"
  },
  "weight_class": "Lightweight"
}
